core/__init__.py
core/admin.py
core/apps.py
core/choices.py
core/models.py
core/tasks.py
core/urls.py
core/views.py
core/migrations/0001_initial.py
core/migrations/__init__.py
nofollow/__init__.py
nofollow/_version.py
nofollow/celery.py
nofollow/settings.py
nofollow/test_settings.py
nofollow/urls.py
nofollow/wsgi.py
web/__init__.py
web/admin.py
web/apps.py
web/models.py
web/tests.py
web/urls.py
web/views.py
web/migrations/__init__.py
web/static/web/scripts/csrf.js
web/static/web/styles/read.css
web/static/web/styles/site.sass
web/templates/web/base.tmpl.html
web/templates/web/feeds.tmpl.html
web/templates/web/links.tmpl.html
web/templates/web/login.tmpl.html
web/templates/web/navigation.tmpl.html
web/templates/web/read.tmpl.html
web/templates/web/submit.tmpl.html
nofollow-0.1.0.dist-info/METADATA
nofollow-0.1.0.dist-info/WHEEL
nofollow-0.1.0.dist-info/top_level.txt
nofollow-0.1.0.dist-info/RECORD
