Metadata-Version: 2.1
Name: nofollow
Version: 0.1.0
Summary: UNKNOWN
Home-page: https://github.com/lullis/nofollow
Author: UNKNOWN
Author-email: UNKNOWN
License: UNKNOWN
Keywords: bookmark-manager syndication html-extraction
Platform: UNKNOWN
Classifier: Environment :: Web Environment
Classifier: Framework :: Django
Classifier: Operating System :: POSIX :: Linux
Classifier: Programming Language :: Python
Classifier: Programming Language :: Python :: 3.5
Classifier: Programming Language :: Python :: 3.6
Classifier: Topic :: Internet :: WWW/HTTP
Classifier: Topic :: Internet :: WWW/HTTP :: Dynamic Content
Requires-Dist: celery
Requires-Dist: django (>=2.0)
Requires-Dist: django-boris
Requires-Dist: django-cindy
Requires-Dist: django-compressor
Requires-Dist: django-kip
Requires-Dist: django-model-utils
Requires-Dist: djangorestframework
Requires-Dist: django-material
Requires-Dist: libsass
Requires-Dist: psycopg2-binary
